{
    "gnb": [
        {
            "nm": "네이버",
            "href": "http://www.naver.com"
        },
        {
            "nm": "다음",
            "href": "http://www.daum.net"
        }
    ],
    "quick": [
        {
            "nm": "깃",
            "href": "https://github.com/",
            "target": "_blank"
        },
        {
            "nm": "유튜브",
            "href": "https://youtube.com/",
            "target": "_blank"
        },
        {
            "nm": "페이스북",
            "href": "https://facebook.com/",
            "target": "_blank"
        }
    ]
}